odoo/addons/sale_last_price_info/README.rst
odoo/addons/sale_last_price_info/__init__.py
odoo/addons/sale_last_price_info/__manifest__.py
odoo/addons/sale_last_price_info/i18n/ca.po
odoo/addons/sale_last_price_info/i18n/de.po
odoo/addons/sale_last_price_info/i18n/es.po
odoo/addons/sale_last_price_info/i18n/fr.po
odoo/addons/sale_last_price_info/i18n/it.po
odoo/addons/sale_last_price_info/i18n/sale_last_price_info.pot
odoo/addons/sale_last_price_info/i18n/sl_SI.po
odoo/addons/sale_last_price_info/models/__init__.py
odoo/addons/sale_last_price_info/models/product.py
odoo/addons/sale_last_price_info/static/description/icon.png
odoo/addons/sale_last_price_info/tests/__init__.py
odoo/addons/sale_last_price_info/tests/test_sale_last_price_info.py
odoo/addons/sale_last_price_info/views/product_view.xml
odoo11_addon_sale_last_price_info-11.0.1.0.0.99.dev8.dist-info/METADATA
odoo11_addon_sale_last_price_info-11.0.1.0.0.99.dev8.dist-info/WHEEL
odoo11_addon_sale_last_price_info-11.0.1.0.0.99.dev8.dist-info/top_level.txt
odoo11_addon_sale_last_price_info-11.0.1.0.0.99.dev8.dist-info/RECORD
